{"logs": [
{ "dataHora": "12/09/2024 22:08:02", "operacao": "Cadastro de usuário", "nome": "admin", "usuario": "Usuário" },
{ "dataHora": "12/09/2024 22:08:11", "operacao": "Login de usuário", "nome": "admin", "usuario": "Usuário" },
{ "dataHora": "12/09/2024 22:12:49", "operacao": "Login de usuário", "nome": "admin", "usuario": "Usuário" },
{ "dataHora": "12/09/2024 22:49:26", "operacao": "Login de usuário", "nome": "admin", "usuario": "Usuário" },
{ "dataHora": "13/09/2024 00:26:46", "operacao": "Login de usuário", "nome": "admin", "usuario": "Usuário" },
{ "dataHora": "13/09/2024 00:32:46", "operacao": "Login de usuário", "nome": "admin", "usuario": "Usuário" },
{ "dataHora": "13/09/2024 00:33:33", "operacao": "Login de usuário", "nome": "admin", "usuario": "Usuário" },
{ "dataHora": "13/09/2024 00:35:33", "operacao": "Login de usuário", "nome": "admin", "usuario": "Usuário" },
{ "dataHora": "13/09/2024 00:36:53", "operacao": "Login de usuário", "nome": "admin", "usuario": "Usuário" },
{ "dataHora": "13/09/2024 00:38:57", "operacao": "Login de usuário", "nome": "admin", "usuario": "Usuário" },
{ "dataHora": "13/09/2024 01:19:08", "operacao": "Login de usuário", "nome": "admin", "usuario": "Usuário" },
{ "dataHora": "13/09/2024 01:20:22", "operacao": "Login de usuário", "nome": "admin", "usuario": "Usuário" },
{ "dataHora": "13/09/2024 01:23:48", "operacao": "Login de usuário", "nome": "admin", "usuario": "Usuário" },
{ "dataHora": "13/09/2024 01:24:32", "operacao": "Login de usuário", "nome": "cat", "usuario": "Usuário" },
{ "dataHora": "13/09/2024 01:27:12", "operacao": "Login de usuário", "nome": "cat", "usuario": "Usuário" },
{ "dataHora": "13/09/2024 01:29:17", "operacao": "Login de usuário", "nome": "cat", "usuario": "Usuário" },
{ "dataHora": "13/09/2024 01:30:46", "operacao": "Login de usuário", "nome": "cat", "usuario": "Usuário" },
{ "dataHora": "13/09/2024 01:31:56", "operacao": "Login de usuário", "nome": "cat", "usuario": "Usuário" },
{ "dataHora": "13/09/2024 01:32:41", "operacao": "Login de usuário", "nome": "cat", "usuario": "Usuário" },
{ "dataHora": "13/09/2024 01:33:58", "operacao": "Login de usuário", "nome": "cat", "usuario": "Usuário" },
{ "dataHora": "13/09/2024 01:35:50", "operacao": "Login de usuário", "nome": "cat", "usuario": "Usuário" },
{ "dataHora": "13/09/2024 01:41:34", "operacao": "Login de usuário", "nome": "cat", "usuario": "Usuário" },
{ "dataHora": "13/09/2024 01:43:15", "operacao": "Login de usuário", "nome": "cat", "usuario": "Usuário" },
{ "dataHora": "13/09/2024 01:45:26", "operacao": "Login de usuário", "nome": "cat", "usuario": "Usuário" },
{ "dataHora": "13/09/2024 01:46:54", "operacao": "Login de usuário", "nome": "cat", "usuario": "Usuário" },
{ "dataHora": "13/09/2024 01:53:38", "operacao": "Login de usuário", "nome": "cat", "usuario": "Usuário" }
]}